Mahanalobis_Detection_Outliers/__init__.py
Mahanalobis_Detection_Outliers/main.py
Mahanalobis_Detection_Outliers-1.0.dist-info/METADATA
Mahanalobis_Detection_Outliers-1.0.dist-info/WHEEL
Mahanalobis_Detection_Outliers-1.0.dist-info/top_level.txt
Mahanalobis_Detection_Outliers-1.0.dist-info/RECORD
